<templates>

    <template id="list">
        <auth />
        <page />
    </template>

    <template id="create">
        <auth required="true"/>
        <body required="true">
            <i name="tags" required="true" list="true" datatype="integer"/>
        </body>
    </template>

    <template id="clear">
        <auth required="true"/>
        <query>
            <q name="ids" />
        </query>
    </template>

    <template id="put">
        <auth required="true"/>
    </template>

    <template id="delete">
        <auth required="true"/>
    </template>

</templates>